jobs_detector/__init__.py
jobs_detector/exceptions.py
jobs_detector/main.py
jobs_detector/settings.py
rmotr_b7_c1_g1_jobs_detectorr-0.0.4.dist-info/DESCRIPTION.rst
rmotr_b7_c1_g1_jobs_detectorr-0.0.4.dist-info/METADATA
rmotr_b7_c1_g1_jobs_detectorr-0.0.4.dist-info/RECORD
rmotr_b7_c1_g1_jobs_detectorr-0.0.4.dist-info/WHEEL
rmotr_b7_c1_g1_jobs_detectorr-0.0.4.dist-info/entry_points.txt
rmotr_b7_c1_g1_jobs_detectorr-0.0.4.dist-info/metadata.json
rmotr_b7_c1_g1_jobs_detectorr-0.0.4.dist-info/top_level.txt
