Metadata-Version: 2.0
Name: rmotr-b7-c1-g1-jobs-detectorr
Version: 0.0.4
Summary: rmotr.com Group Project | Jobs Detector
Home-page: UNKNOWN
Author: rmotr.com
Author-email: jessica.ngo@live.com
License: CC BY-SA 4.0 License
Platform: UNKNOWN
Requires-Dist: click
Requires-Dist: responses
